pytest_easy_server/__init__.py
pytest_easy_server/_easy_server_fixture.py
pytest_easy_server/_version.py
pytest_easy_server/plugin.py
pytest_easy_server-0.8.0.dist-info/LICENSE
pytest_easy_server-0.8.0.dist-info/METADATA
pytest_easy_server-0.8.0.dist-info/WHEEL
pytest_easy_server-0.8.0.dist-info/entry_points.txt
pytest_easy_server-0.8.0.dist-info/top_level.txt
pytest_easy_server-0.8.0.dist-info/zip-safe
pytest_easy_server-0.8.0.dist-info/RECORD
