Metadata-Version: 2.1
Name: pytest-easy-server
Version: 0.8.0
Summary: Pytest plugin for easy testing against servers
Home-page: https://github.com/andy-maier/pytest-easy-server
Author: Andreas Maier
Author-email: andreas.r.maier@gmx.de
Maintainer: Andreas Maier
Maintainer-email: andreas.r.maier@gmx.de
License: Apache Software License 2.0
Project-URL: Bug Tracker, https://github.com/andy-maier/pytest-easy-server/issues
Project-URL: Documentation, https://pytest-easy-server.readthedocs.io/en/stable/
Project-URL: Change Log, https://pytest-easy-server.readthedocs.io/en/stable/changes.html
Platform: any
Classifier: Development Status :: 4 - Beta
Classifier: Environment :: Console
Classifier: Intended Audience :: Developers
Classifier: License :: OSI Approved :: Apache Software License
Classifier: Operating System :: OS Independent
Classifier: Programming Language :: Python :: 2
Classifier: Programming Language :: Python :: 2.7
Classifier: Programming Language :: Python :: 3
Classifier: Programming Language :: Python :: 3.4
Classifier: Programming Language :: Python :: 3.5
Classifier: Programming Language :: Python :: 3.6
Classifier: Programming Language :: Python :: 3.7
Classifier: Programming Language :: Python :: 3.8
Classifier: Programming Language :: Python :: 3.9
Classifier: Topic :: Software Development :: Libraries :: Python Modules
Requires-Python: >=2.7, !=3.0.*, !=3.1.*, !=3.2.*, !=3.3.*
Requires-Dist: easy-server (>=0.8.0)
Requires-Dist: easy-vault (>=0.7.0)
Requires-Dist: yamlloader (>=0.5.5)
Requires-Dist: jsonschema (>=2.6.0)
Requires-Dist: pytest (<5.0.0,>=4.3.1) ; python_version < "3.5"
Requires-Dist: PyYAML (>=5.3.1) ; python_version == "2.7"
Requires-Dist: pyrsistent (<0.16.0,>=0.14.0) ; python_version == "2.7"
Requires-Dist: PyYAML (<5.3,>=5.2) ; python_version == "3.4"
Requires-Dist: pyrsistent (<0.15.0,>=0.14.0) ; python_version == "3.4"
Requires-Dist: PyYAML (>=5.3.1) ; python_version > "3.4"
Requires-Dist: pluggy (>=0.7.1) ; python_version >= "2.7" and python_version <= "3.6"
Requires-Dist: pyrsistent (>=0.14.0) ; python_version >= "3.5"
Requires-Dist: pytest (>=4.3.1) ; python_version >= "3.5" and python_version <= "3.6"
Requires-Dist: pytest (>=4.4.0) ; python_version >= "3.7"
Requires-Dist: pluggy (>=0.13.0) ; python_version >= "3.7"
